arsla/__init__.py
arsla/builtins.py
arsla/cli.py
arsla/errors.py
arsla/interpreter.py
arsla/lexer.py
arsla/parser.py
arsla_lang-0.1.0.dist-info/licenses/LICENSE
arsla_lang-0.1.0.dist-info/METADATA
arsla_lang-0.1.0.dist-info/WHEEL
arsla_lang-0.1.0.dist-info/entry_points.txt
arsla_lang-0.1.0.dist-info/top_level.txt
arsla_lang-0.1.0.dist-info/RECORD
