Metadata-Version: 2.4
Name: arsla-lang
Version: 0.1.0
Summary: Arsla: A concise code golfing language for expressive problem-solving
Author-email: Aitzaz Imtiaz <aitzazimtiaz.ai@gmail.com>
License: MIT
Project-URL: Repository, https://github.com/aitzazimtiaz/arsla-lang
Project-URL: Homepage, https://github.com/aitzazimtiaz/arsla-lang
Project-URL: Documentation, https://github.com/aitzazimtiaz/arsla--lang/wiki
Keywords: code-golf,programming-language,interpreter
Classifier: Development Status :: 3 - Alpha
Classifier: Intended Audience :: Developers
Classifier: License :: OSI Approved :: MIT License
Classifier: Programming Language :: Python :: 3
Classifier: Programming Language :: Python :: 3.8
Classifier: Programming Language :: Python :: 3.9
Classifier: Programming Language :: Python :: 3.10
Classifier: Programming Language :: Python :: 3.11
Classifier: Programming Language :: Python :: 3.12
Classifier: Topic :: Software Development :: Interpreters
Classifier: Topic :: Games/Entertainment :: Puzzle Games
Requires-Python: >=3.8
License-File: LICENSE
Requires-Dist: rich>=13.0
Provides-Extra: dev
Requires-Dist: pytest>=8.0; extra == "dev"
Requires-Dist: black>=24.0; extra == "dev"
Requires-Dist: ruff>=0.3.0; extra == "dev"
Requires-Dist: mypy>=1.8.0; extra == "dev"
Requires-Dist: coverage>=7.0; extra == "dev"
Requires-Dist: twine>=4.0; extra == "dev"
Requires-Dist: sphinx>=7.0; extra == "dev"
Dynamic: license-file
